
[ 
  
    {
      "filename": "DSC02485.jpg",
      "alt": "heavy drapes shot into large window from sidewalk"
     },
       {
      "filename": "DSC1344.jpg",
      "alt": "young man looking back"
    },

     {
      "filename":  "DSC3275.jpg",
      "alt": "flower meadow"
     },
          {
        "filename": "IMG_9515.jpg",
        "alt":"paddle in window"
     },


    {
      "filename": "DSC2962.jpg",
      "alt": "katherine headshot"
     },

         {
    "filename": "DSC00778.jpg",
    "alt": "a window filled with plants and a clay hanging pot"
     },

     {
      "filename": "DSC2360.jpg",
      "alt": "walking under tree canopy"
     },
    
 

 
   
     {
          "filename":  "IMG_4308.jpg",
        "alt":  "window reflection water bottle propping it open"
     },
     {
        "filename":  "DSC06776.jpg",
        "alt":"closeup of young mans face"
     },
           {
        "filename": "DSC00697.jpg",
        "alt":  "upshot of a tree"
     },
    {
        "filename": "DSC_0331.jpg",
        "alt":"green car in front of green house"
     },
     {
        "filename": "IMG_3554.jpg",
        "alt":   "beach volleyball pole"
     },
 
     {
        "filename":  "IMG_6494.jpg",
        "alt":  "drainage hole in wall"
     },
     {
       
         "filename":  "IMG_9602.jpg",
         "alt":  "woman sweeping driveway"
     },
    
   
       {
         "filename":  "DSC01224.jpg",
         "alt":  "white building blue door"
     },    {
         "filename":  "IMG_6332.jpg",
         "alt":  "man in police car"
     },

         {
        "filename":  "IMG_6213.jpg",
        "alt":  "bottom of sailboat on stand"
     },
        {
        "filename":  "DSC00925.jpg",
        "alt":  "winter alley in toronto"
     },
        {
        "filename":  "IMG_2834.jpg",
        "alt":  "baby just born"
     },
     {
        "filename":  "P8090075.jpg",
        "alt":  "fork in the road"
     }


        

     






      

]

